concat_js/__about__.py
concat_js/__init__.py
concat_js/dep_graph.py
concat_js/settings.py
concat_js/watch_src.py
concat_js/management/__init__.py
concat_js/management/commands/__init__.py
concat_js/management/commands/watch_js.py
concat_js/test_app/__init__.py
concat_js/test_app/manage.py
concat_js/test_app/settings.py
concat_js/test_app/settings_base.py
concat_js/test_app/tests.py
concat_js/test_app/urls.py
concat_js/test_app/wsgi.py
django_concat_js-0.3.2.dist-info/METADATA
django_concat_js-0.3.2.dist-info/WHEEL
django_concat_js-0.3.2.dist-info/licenses/LICENSE.txt
django_concat_js-0.3.2.dist-info/RECORD
